metats/__init__.py
metats/datasets.py
metats/generators.py
metats/pipeline.py
metats/features/__init__.py
metats/features/deep.py
metats/features/statistical.py
metats/features/unsupervised.py
metats/forecasters/__init__.py
metats/forecasters/statistical.py
metats/forecasters/utils.py
metats/forecasters/wrappers.py
metats/metalearners/deep.py
metats-0.2.1.dist-info/LICENSE
metats-0.2.1.dist-info/METADATA
metats-0.2.1.dist-info/WHEEL
metats-0.2.1.dist-info/entry_points.txt
metats-0.2.1.dist-info/top_level.txt
metats-0.2.1.dist-info/RECORD
