Metadata-Version: 2.1
Name: metats
Version: 0.2.1
Summary: Meta-Learning for Time Series Forecasting
Author-email: Sasan Barak <s.barak@soton.ac.uk>, Amirabbas Asadi <amir137825@gmail.com>, Mohammad Joshaghani <mjoshaghani10@gmail.com>
License: MIT License
Project-URL: Homepage, https://drsasanbarak.github.io/metats/
Keywords: timeseries,metalearning,forecasting,unsupervised learning,deeplearning,machine learning
Classifier: License :: OSI Approved :: MIT License
Classifier: Programming Language :: Python
Classifier: Programming Language :: Python :: 3
License-File: LICENSE
Requires-Dist: torch (>=1.12.1)
Requires-Dist: umap-learn (>=0.5.3)
Requires-Dist: darts (>=0.20.0)
Requires-Dist: lightgbm (>=3.2.1)
Requires-Dist: matplotlib (>=3.4.2)
Requires-Dist: numba (>=0.55.1)
Requires-Dist: numpy (==1.23.5)
Requires-Dist: pandas (>=1.2.4)
Requires-Dist: pbr (>=5.11.1)
Requires-Dist: pdoc (>=12.0.2)
Requires-Dist: scikit-learn (>=1.0.2)
Requires-Dist: scipy (>=1.6.3)
Requires-Dist: seaborn (>=0.11.1)
Requires-Dist: shap (>=0.40.0)
Requires-Dist: sktime (>=0.10.0)
Requires-Dist: tqdm (>=4.60.0)
Requires-Dist: tsfresh (==0.19.0)
Requires-Dist: statsforecast (>=1.5.0)
Provides-Extra: dev
Requires-Dist: pytest ; extra == 'dev'
Requires-Dist: pdoc ; extra == 'dev'
